cosmicdb/__init__.py
cosmicdb/admin.py
cosmicdb/apps.py
cosmicdb/forms.py
cosmicdb/models.py
cosmicdb/tables.py
cosmicdb/tests.py
cosmicdb/treedump.json
cosmicdb/urls.py
cosmicdb/views.py
cosmicdb/widgets.py
cosmicdb/__pycache__/__init__.cpython-38.pyc
cosmicdb/__pycache__/admin.cpython-38.pyc
cosmicdb/__pycache__/forms.cpython-38.pyc
cosmicdb/__pycache__/models.cpython-38.pyc
cosmicdb/__pycache__/tables.cpython-38.pyc
cosmicdb/__pycache__/urls.cpython-38.pyc
cosmicdb/__pycache__/views.cpython-38.pyc
cosmicdb/migrations/0001_initial.py
cosmicdb/migrations/__init__.py
cosmicdb/migrations/__pycache__/0001_initial.cpython-38.pyc
cosmicdb/migrations/__pycache__/__init__.cpython-38.pyc
cosmicdb/static/cosmicdb/favicon.ico
cosmicdb/static/cosmicdb/img/databases.png
cosmicdb/static/cosmicdb/img/demo1.png
cosmicdb/static/cosmicdb/img/demo2.png
cosmicdb/static/cosmicdb/img/demo3.png
cosmicdb/static/cosmicdb/img/djangologo.png
cosmicdb/static/cosmicdb/img/icon.png
cosmicdb/static/cosmicdb/img/icon300.png
cosmicdb/static/cosmicdb/js/jquery-3.3.1.min.js
cosmicdb/static/cosmicdb/js/moment/moment.js
cosmicdb/static/cosmicdb/js/pickadate/legacy.js
cosmicdb/static/cosmicdb/js/pickadate/picker.date.js
cosmicdb/static/cosmicdb/js/pickadate/picker.js
cosmicdb/static/cosmicdb/js/pickadate/picker.time.js
cosmicdb/static/cosmicdb/js/pickadate/compressed/legacy.js
cosmicdb/static/cosmicdb/js/pickadate/compressed/picker.date.js
cosmicdb/static/cosmicdb/js/pickadate/compressed/picker.js
cosmicdb/static/cosmicdb/js/pickadate/compressed/picker.time.js
cosmicdb/static/cosmicdb/js/pickadate/compressed/themes/classic.css
cosmicdb/static/cosmicdb/js/pickadate/compressed/themes/classic.date.css
cosmicdb/static/cosmicdb/js/pickadate/compressed/themes/classic.time.css
cosmicdb/static/cosmicdb/js/pickadate/compressed/themes/default.css
cosmicdb/static/cosmicdb/js/pickadate/compressed/themes/default.date.css
cosmicdb/static/cosmicdb/js/pickadate/compressed/themes/default.time.css
cosmicdbsemantic-0.0.39.dist-info/LICENSE.txt
cosmicdbsemantic-0.0.39.dist-info/METADATA
cosmicdbsemantic-0.0.39.dist-info/WHEEL
cosmicdbsemantic-0.0.39.dist-info/top_level.txt
cosmicdbsemantic-0.0.39.dist-info/RECORD
